optinum/__init__.py
optinum/base_ops.py
optinum/eigen.py
optinum/ode.py
optinum/signal.py
optinum/sparse.py
optinum/spectrum.py
optinum/plotting/__init__.py
optinum/plotting/eigen.py
optinum/plotting/ode.py
optinum-0.3.2.dist-info/METADATA
optinum-0.3.2.dist-info/WHEEL
optinum-0.3.2.dist-info/top_level.txt
optinum-0.3.2.dist-info/RECORD
